[{"name":"Banana Smoothie","description":null,"portions":2,"citation":null,"deleted_at":null,"rows":[{"ingredient":"Banana","delta":0,"unit":"quantity","value":2,"weight":366},{"ingredient":"Vanilla yogurt","delta":1,"unit":"cup","value":1,"weight":245},{"ingredient":"Whole milk","delta":2,"unit":"cup","value":1,"weight":230},{"ingredient":"Honey","delta":3,"unit":"teaspoon","value":2,"weight":14.16667},{"ingredient":"Cinnamon","delta":4,"unit":"pinch","value":1,"weight":0.165},{"ingredient":"Ice","delta":5,"unit":"cup","value":1,"weight":140}],"directions":[]},{"name":"Strawberry Banana","description":"A strawberryey bananaery blend of strawberries and bananas.","portions":2,"citation":null,"deleted_at":null,"rows":[{"ingredient":"Banana","delta":0,"unit":"quantity","value":1,"weight":183},{"ingredient":"Strawberries, fresh","delta":1,"unit":"cup","value":1,"weight":200},{"ingredient":"Vanilla yogurt","delta":2,"unit":"cup","value":1,"weight":245},{"ingredient":"Whole milk","delta":3,"unit":"cup","value":1,"weight":230},{"ingredient":"Honey","delta":4,"unit":"teaspoon","value":2,"weight":14.16667},{"ingredient":"Cinnamon","delta":5,"unit":"pinch","value":1,"weight":0.165},{"ingredient":"Ice","delta":6,"unit":"cup","value":1,"weight":140}],"directions":[]},{"name":"Triple Berry Blend","description":null,"portions":2,"citation":null,"deleted_at":null,"rows":[{"ingredient":"Blackberries, frozen","delta":0,"unit":"cup","value":1,"weight":150},{"ingredient":"Strawberries, frozen","delta":1,"unit":"cup","value":1,"weight":150},{"ingredient":"Raspberries, frozen","delta":2,"unit":"cup","value":1,"weight":130},{"ingredient":"Ice","delta":3,"unit":"cup","value":1,"weight":140},{"ingredient":"Whole milk","delta":4,"unit":"cup","value":1,"weight":230}],"directions":[]},{"name":"Zesty Orange Zucchini","description":null,"portions":2,"citation":null,"deleted_at":null,"rows":[{"ingredient":"Courgette","delta":0,"unit":"quantity","value":1,"weight":200},{"ingredient":"Lemon","delta":1,"unit":"quantity","value":1,"weight":70},{"ingredient":"Flaxseed","delta":2,"unit":"table_spoon","value":1,"weight":12.425},{"ingredient":"Orange","delta":3,"unit":"quantity","value":1,"weight":241},{"ingredient":"Turmeric","delta":4,"unit":"teaspoon","value":1,"weight":3.125},{"ingredient":"Coconut water","delta":5,"unit":"cup","value":1,"weight":240}],"directions":[]},{"name":"Banana Nectarine Chard","description":null,"portions":2,"citation":null,"deleted_at":null,"rows":[{"ingredient":"Swiss chard","delta":0,"unit":"ounce","value":2,"weight":56.69904},{"ingredient":"Nectarine","delta":1,"unit":"quantity","value":1,"weight":142},{"ingredient":"Water","delta":2,"unit":"cup","value":1,"weight":237},{"ingredient":"Banana","delta":3,"unit":"quantity","value":1,"weight":183},{"ingredient":"Chia seeds","delta":4,"unit":"table_spoon","value":1,"weight":12.05521},{"ingredient":"Ice","delta":5,"unit":"cup","value":0,"weight":0}],"directions":[]},{"name":"Banana Ginger Smoothie","description":null,"portions":2,"citation":"https:\/\/www.prevention.com\/food\/20-super-healthy-smoothie-recipes\/slide\/2","deleted_at":null,"rows":[{"ingredient":"Banana","delta":0,"unit":"quantity","value":1,"weight":183},{"ingredient":"Vanilla yogurt","delta":1,"unit":"cup","value":1,"weight":245},{"ingredient":"Honey","delta":2,"unit":"teaspoon","value":1,"weight":7.08333},{"ingredient":"Ginger","delta":3,"unit":"teaspoon","value":1,"weight":2}],"directions":[]},{"name":"Orange Dream Creamsicle","description":null,"portions":1,"citation":"https:\/\/www.prevention.com\/food\/20-super-healthy-smoothie-recipes\/slide\/3","deleted_at":null,"rows":[{"ingredient":"Orange","delta":0,"unit":"quantity","value":1,"weight":241},{"ingredient":"Plain low fat yogurt","delta":1,"unit":"cup","value":0,"weight":61.25},{"ingredient":"Frozen orange juice concentrate","delta":2,"unit":"table_spoon","value":2,"weight":20.70833},{"ingredient":"Vanilla extract","delta":3,"unit":"teaspoon","value":0,"weight":0},{"ingredient":"Ice","delta":4,"unit":"cup","value":0,"weight":0}],"directions":[]}]